giza/zkcook/__init__.py
giza/zkcook/model_reducer.py
giza/zkcook/model_toolkit/__init__.py
giza/zkcook/model_toolkit/custom_transformers/__init__.py
giza/zkcook/model_toolkit/custom_transformers/customPCA.py
giza/zkcook/model_toolkit/custom_transformers/customRFE.py
giza/zkcook/model_toolkit/data_transformer.py
giza/zkcook/model_toolkit/feature_models_space.py
giza/zkcook/model_toolkit/metrics.py
giza/zkcook/model_toolkit/model_evaluator.py
giza/zkcook/model_toolkit/model_info.py
giza/zkcook/model_toolkit/model_penalicer.py
giza/zkcook/model_toolkit/model_trainer.py
giza/zkcook/serializer/__init__py
giza/zkcook/serializer/lgbm.py
giza/zkcook/serializer/serialize.py
giza/zkcook/serializer/xg.py
giza_zkcook-0.2.2.dist-info/LICENSE
giza_zkcook-0.2.2.dist-info/METADATA
giza_zkcook-0.2.2.dist-info/WHEEL
giza_zkcook-0.2.2.dist-info/RECORD
